pymongtic/__init__.py
pymongtic/base.py
pymongtic/config.py
pymongtic/connect.py
pymongtic/decorators.py
pymongtic/exceptions.py
pymongtic/indexes.py
pymongtic/views.py
pymongtic-0.1.0.dist-info/WHEEL
pymongtic-0.1.0.dist-info/METADATA
pymongtic-0.1.0.dist-info/RECORD
